NCBDC_zdzzsc/__init__.py
NCBDC_zdzzsc/calculate.py
NCBDC_zdzzsc-0.0.3.dist-info/METADATA
NCBDC_zdzzsc-0.0.3.dist-info/WHEEL
NCBDC_zdzzsc-0.0.3.dist-info/top_level.txt
NCBDC_zdzzsc-0.0.3.dist-info/RECORD
